quicksom/__init__.py
quicksom/dcd_reader.py
quicksom/main.py
quicksom/som.py
quicksom/somapp.py
quicksom/somax.py
quicksom/somgui.py
quicksom/test_errors.py
quicksom/bin/__init__.py
quicksom-1.0.0.data/scripts/dcd2npy
quicksom-1.0.0.data/scripts/mdx
quicksom-1.0.0.data/scripts/quicksom_extract
quicksom-1.0.0.data/scripts/quicksom_fit
quicksom-1.0.0.data/scripts/quicksom_flow
quicksom-1.0.0.data/scripts/quicksom_gui
quicksom-1.0.0.data/scripts/quicksom_predict
quicksom-1.0.0.data/scripts/quicksom_project
quicksom-1.0.0.dist-info/LICENSE
quicksom-1.0.0.dist-info/METADATA
quicksom-1.0.0.dist-info/WHEEL
quicksom-1.0.0.dist-info/top_level.txt
quicksom-1.0.0.dist-info/RECORD
