Metadata-Version: 2.1
Name: quicksom
Version: 1.0.0
Summary: Self Organizing Maps efficient implementation using PyTorch and JAX
Home-page: https://github.com/bougui505/quicksom
Author: Vincent Mallet and Michael Nilges and Guillaume Bouvier
Author-email: vincent.mallet96@gmail.com
License: UNKNOWN
Platform: UNKNOWN
Classifier: Programming Language :: Python :: 3
Classifier: License :: OSI Approved :: MIT License
Classifier: Operating System :: OS Independent
Requires-Python: >=3.5
License-File: LICENSE
Requires-Dist: numpy (>1.0)
Requires-Dist: scipy (>0.1)
Requires-Dist: scikit-image (>0.15)
Requires-Dist: scikit-learn (>0.22)
